qshell/__init__.py
qshell/command.py
qshell/shell.py
qshell-0.2.6.dist-info/LICENSE
qshell-0.2.6.dist-info/METADATA
qshell-0.2.6.dist-info/WHEEL
qshell-0.2.6.dist-info/top_level.txt
qshell-0.2.6.dist-info/RECORD
