Metadata-Version: 2.1
Name: qshell
Version: 0.2.6
Summary: A interactive command shell wrapper from python projects
Home-page: UNKNOWN
Author: QSoloX
Author-email: UNKNOWN
License: MIT
Platform: UNKNOWN
Requires-Dist: colorama
